freerouting/__init__.py
freerouting/client.py
freerouting_client-2.1.1.dist-info/licenses/LICENSE
freerouting_client-2.1.1.dist-info/METADATA
freerouting_client-2.1.1.dist-info/WHEEL
freerouting_client-2.1.1.dist-info/top_level.txt
freerouting_client-2.1.1.dist-info/RECORD
