Metadata-Version: 2.4
Name: freerouting-client
Version: 2.1.1
Summary: The official Python client library for the Freerouting API (api.freerouting.app), an open-source, advanced PCB (printed circuit board) auto-router
Author-email: Andras Fuchs <info@freerouting.app>
License: MIT License
Project-URL: Homepage, https://www.freerouting.app
Project-URL: Repository, https://github.com/freerouting/freerouting-python-client
Project-URL: Bug Tracker, https://github.com/freerouting/freerouting-python-client/issues
Project-URL: Documentation, https://github.com/freerouting/freerouting/blob/master/docs/API_v1.md
Keywords: freerouting,pcb,printed circuit board,router,autorouter,api,eda,electronics,circuits,client
Classifier: Development Status :: 3 - Alpha
Classifier: Intended Audience :: Developers
Classifier: Intended Audience :: Science/Research
Classifier: License :: OSI Approved :: Apache Software License
Classifier: Operating System :: OS Independent
Classifier: Programming Language :: Python :: 3
Classifier: Programming Language :: Python :: 3.7
Classifier: Programming Language :: Python :: 3.8
Classifier: Programming Language :: Python :: 3.9
Classifier: Programming Language :: Python :: 3.10
Classifier: Programming Language :: Python :: 3.11
Classifier: Programming Language :: Python :: 3.12
Classifier: Topic :: Software Development :: Libraries :: Python Modules
Classifier: Topic :: Scientific/Engineering :: Electronic Design Automation (EDA)
Requires-Python: >=3.7
License-File: LICENSE
Requires-Dist: requests>=2.20.0
Dynamic: license-file
